deeplightrag/__init__.py
deeplightrag/cli.py
deeplightrag/core.py
deeplightrag/interfaces.py
deeplightrag/graph/__init__.py
deeplightrag/graph/dual_layer.py
deeplightrag/graph/entity_relationship.py
deeplightrag/graph/visual_spatial.py
deeplightrag/ner/__init__.py
deeplightrag/ner/enhanced_ner_pipeline.py
deeplightrag/ner/entity_filter.py
deeplightrag/ner/entity_processor.py
deeplightrag/ner/entity_schema.py
deeplightrag/ner/entity_type_mapper.py
deeplightrag/ner/gliner_ner.py
deeplightrag/ner/text_classifier.py
deeplightrag/ner/working_enhanced_ner.py
deeplightrag/ner/working_gliner_ner.py
deeplightrag/ocr/__init__.py
deeplightrag/ocr/deepseek_model.py
deeplightrag/ocr/deepseek_ocr.py
deeplightrag/ocr/geometry.py
deeplightrag/ocr/processor.py
deeplightrag/ocr/visual_token.py
deeplightrag/retrieval/__init__.py
deeplightrag/retrieval/adaptive_retriever.py
deeplightrag/retrieval/query_classifier.py
deeplightrag/retrieval/visual_aware_retriever.py
deeplightrag/utils/__init__.py
deeplightrag/utils/config_manager.py
deeplightrag/utils/device.py
deeplightrag/utils/helpers.py
deeplightrag-1.0.22.dist-info/licenses/LICENSE
deeplightrag-1.0.22.dist-info/METADATA
deeplightrag-1.0.22.dist-info/WHEEL
deeplightrag-1.0.22.dist-info/entry_points.txt
deeplightrag-1.0.22.dist-info/top_level.txt
deeplightrag-1.0.22.dist-info/RECORD
